sample_cli/__init__.py
sample_cli/app.py
sample_cli/cli.py
sample_cli/config.py
sample_cli/contracts.py
sample_cli/sample-cli.toml
mattk09_sample_cli-0.1.3.dist-info/METADATA
mattk09_sample_cli-0.1.3.dist-info/WHEEL
mattk09_sample_cli-0.1.3.dist-info/entry_points.txt
mattk09_sample_cli-0.1.3.dist-info/RECORD
